README
setup.py
bin/fastly_purge_url.py
bin/fastly_upload_vcl.py
cdn_fastly.egg-info/PKG-INFO
cdn_fastly.egg-info/SOURCES.txt
cdn_fastly.egg-info/dependency_links.txt
cdn_fastly.egg-info/top_level.txt
fastly/__init__.py
tests/__init__.py