Metadata-Version: 1.1
Name: cdn-fastly
Version: 1.0.4
Summary: A Python client libary for the Fastly API.
Home-page: https://github.com/obulpathi/cdn-fastly-python
Author: Obulapathi N Challa
Author-email: obulpathi@gmail.com
License: BSD
Keywords: fastly
Platform: UNKNOWN
Classifier: Development Status :: 3 - Alpha
Classifier: Topic :: Software Development :: Libraries :: Python Modules
Classifier: License :: OSI Approved :: BSD License
